MANIFEST.in
README.txt
setup.py
docs/HISTORY.txt
docs/LICENSE.txt
docs/TODO.txt
silva/__init__.py
silva.export.opendocument.egg-info/PKG-INFO
silva.export.opendocument.egg-info/SOURCES.txt
silva.export.opendocument.egg-info/dependency_links.txt
silva.export.opendocument.egg-info/namespace_packages.txt
silva.export.opendocument.egg-info/not-zip-safe
silva.export.opendocument.egg-info/requires.txt
silva.export.opendocument.egg-info/top_level.txt
silva/export/__init__.py
silva/export/opendocument/__init__.py
silva/export/opendocument/adapters.py
silva/export/opendocument/configure.zcml
silva/export/opendocument/templates/manifest.xml
silva/export/opendocument/templates/odt_template.zip
silva/export/opendocument/templates/silva2odt.xslt