Metadata-Version: 1.1
Name: silva.export.opendocument
Version: 1.1
Summary: Export Silva Document and Silva Publication to Open Document
Home-page: https://svn.infrae.com/silva.export.opendocument/trunk
Author: Sylvain Viollon
Author-email: info@infrae.com
License: BSD
Keywords: silva opendocument export
Platform: UNKNOWN
Classifier: Framework :: Zope2
Classifier: Programming Language :: Python
Classifier: Topic :: Software Development :: Libraries :: Python Modules
Classifier: License :: OSI Approved :: BSD License
